<model>
    <instance>
        <new_member_registration_form_without_qr encounter_type="New Member Registration"
            id="new_member_registration_form_without_qr" version="201608160534">
            <formhub>
                <uuid />
            </formhub>
            <provider_uc />
            <provider_town />
            <provider_city />
            <provider_province />
            <provider_location_id openmrs_entity="encounter" openmrs_entity_id="location_id" />
            <provider_location_name />
            <existing_household_id openmrs_entity="person_attribute"
                openmrs_entity_id="household_identifier" />
            <existing_first_name_hhh />
            <existing_last_name_hhh />
            <existing_landmark />
            <existing_address1 />
            <existing_union_council />
            <existing_town />
            <existing_city_village />
            <existing_province />
            <existing_union_councilname />
            <existing_townname />
            <existing_city_villagename />
            <existing_provincename />
            <existing_program_client_id openmrs_entity="person_identifier"
                openmrs_entity_id="Program Client ID" />
            <provider_location_note />
            <start openmrs_entity="concept"
                openmrs_entity_id="163137AAAAAAAAAAAAAAAAAAAAAAAAAAAAAA" />
            <end openmrs_entity="concept"
                openmrs_entity_id="163138AAAAAAAAAAAAAAAAAAAAAAAAAAAAAA" />
            <today openmrs_entity="concept"
                openmrs_entity_id="163286AAAAAAAAAAAAAAAAAAAAAAAAAAAAAA" />
            <deviceid openmrs_entity="concept"
                openmrs_entity_id="163149AAAAAAAAAAAAAAAAAAAAAAAAAAAAAA" />
            <subscriberid openmrs_entity="concept"
                openmrs_entity_id="163150AAAAAAAAAAAAAAAAAAAAAAAAAAAAAA" />
            <simserial openmrs_entity="concept"
                openmrs_entity_id="163151AAAAAAAAAAAAAAAAAAAAAAAAAAAAAA" />
            <phonenumber openmrs_entity="concept"
                openmrs_entity_id="163152AAAAAAAAAAAAAAAAAAAAAAAAAAAAAA" />
            <date openmrs_entity="encounter" openmrs_entity_id="encounter_date" />
            <household_id />
            <name_hhh />
            <address />
            <individual openmrs_entity="person" openmrs_entity_id="household_member_registration">
                <program_client_id />
                <person_id openmrs_entity="person_identifier" openmrs_entity_id="Person ID" />
                <first_name openmrs_entity="person" openmrs_entity_id="first_name" />
                <last_name openmrs_entity="person" openmrs_entity_id="last_name" />
                <gender openmrs_entity="person" openmrs_entity_id="gender" />
                <ethnicity openmrs_entity="concept"
                    openmrs_entity_id="163153AAAAAAAAAAAAAAAAAAAAAAAAAAAAAA" />
                <ethnicity_other openmrs_entity="concept"
                    openmrs_entity_id="160632AAAAAAAAAAAAAAAAAAAAAAAAAAAAAA"
                    openmrs_entity_parent="163330AAAAAAAAAAAAAAAAAAAAAAAAAAAAAA" />
                <relationship openmrs_entity="concept"
                    openmrs_entity_id="163354AAAAAAAAAAAAAAAAAAAAAAAAAAAAAA" />
                <relationship_other openmrs_entity="concept"
                    openmrs_entity_id="160632AAAAAAAAAAAAAAAAAAAAAAAAAAAAAA"
                    openmrs_entity_parent="163355AAAAAAAAAAAAAAAAAAAAAAAAAAAAAA" />
                <member_birthdate_known>yes</member_birthdate_known>
                <member_birthdate />
                <age />
                <calc_age />
                <calc_dob />
                <calc_dob_confirm openmrs_entity="person" openmrs_entity_id="birthdate" />
                <calc_dob_estimated openmrs_entity="person"
                    openmrs_entity_id="birthdate_estimated" />
                <calc_age_confirm openmrs_entity="concept"
                    openmrs_entity_id="154384AAAAAAAAAAAAAAAAAAAAAAAAAAAAAA" />
                <member_birthdate_note />
                <note_age />
                <is_child />
                <note_child3 />
                <is_rep_woman />
                <note_rep_women />
            </individual>
            <comments openmrs_entity="concept"
                openmrs_entity_id="161011AAAAAAAAAAAAAAAAAAAAAAAAAAAAAA" />
            <meta>
                <instanceID />
            </meta>
        </new_member_registration_form_without_qr>
    </instance>
</model>