{"name":"NewbornInformation","title":"নবজাতকের তথ্য","sms_keyword":"NewbornInformation","default_language":"Bengali","instance":{"encounter_type":"Newborn Infromation"},"version":"201602081330","id_string":"NewbornInformation","type":"survey","children":[{"type":"start","name":"start"},{"type":"today","name":"today"},{"bind":{"required":"yes"},"type":"date","name":"DATE_OF_REG","label":{"Bengali":"রেজিস্ট্রেশন তারিখ"}},{"label":{"Bengali":"Birth weight, qualitative"},"type":"select one","children":[{"name":"0","label":{"Bengali":"Normal"}},{"name":"1","label":{"Bengali":"Low"}},{"name":"2","label":{"Bengali":"High"}}],"name":"Birth_Weigtht"},{"label":{"Bengali":"Newborn care received"},"type":"select all that apply","children":[{"name":"0","label":{"Bengali":"Delayed bathing"}},{"name":"1","label":{"Bengali":"Breastfed within 1 hour of birth"}},{"name":"2","label":{"Bengali":"Immedicate thermal care"}}],"name":"Newborn_Care_Received"},{"type":"end","name":"end"},{"control":{"bodyless":true},"type":"group","children":[{"bind":{"readonly":"true()","calculate":"concat('uuid:', uuid())"},"type":"calculate","name":"instanceID"}],"name":"meta"}]}